console_gpt/__init__.py
console_gpt/console_gpt.py
console_gpt-0.5.dist-info/METADATA
console_gpt-0.5.dist-info/WHEEL
console_gpt-0.5.dist-info/top_level.txt
console_gpt-0.5.dist-info/RECORD
