Metadata-Version: 2.1
Name: console-gpt
Version: 0.5
Summary: A package to interact with ChatbotGPT
Home-page: UNKNOWN
Author: Pranav Chandran
Author-email: pranav.chandran@gmail.com
License: UNKNOWN
Platform: UNKNOWN
Classifier: Programming Language :: Python :: 3.9
Classifier: License :: OSI Approved :: MIT License
Classifier: Operating System :: OS Independent
Requires-Dist: openai
